setup.cfg
setup.py
Decoding/ECoG_Decoding.py
Decoding/ModelMaker.py
Decoding/__init__.py
ECoG_Decoding.egg-info/PKG-INFO
ECoG_Decoding.egg-info/SOURCES.txt
ECoG_Decoding.egg-info/dependency_links.txt
ECoG_Decoding.egg-info/requires.txt
ECoG_Decoding.egg-info/top_level.txt