Metadata-Version: 1.1
Name: ECoG-Decoding
Version: 0.1
Summary: Deep Learning for ECoG
Home-page: https://github.com/jacobzweig/ECoG_Decoding
Author: Jacob Zweig
Author-email: jacob.zweig@gmail.com
License: MIT
Download-URL: https://github.com/jacobzweig/ECoG_Decoding/tarball/0.2.0
Platform: UNKNOWN
